agent_sentinel/__init__.py
agent_sentinel/cli.py
agent_sentinel/core/__init__.py
agent_sentinel/core/config.py
agent_sentinel/core/constants.py
agent_sentinel/core/event_registry.py
agent_sentinel/core/exceptions.py
agent_sentinel/core/log_generator.py
agent_sentinel/core/report_generator.py
agent_sentinel/core/sentinel.py
agent_sentinel/core/threat_report_generator.py
agent_sentinel/core/types.py
agent_sentinel/detection/__init__.py
agent_sentinel/detection/detectors.py
agent_sentinel/detection/engine.py
agent_sentinel/detection/enhanced_engine.py
agent_sentinel/detection/enterprise_detectors.py
agent_sentinel/detection/multi_layer_engine.py
agent_sentinel/enterprise/threat_intelligence.py
agent_sentinel/infrastructure/__init__.py
agent_sentinel/infrastructure/async_processing.py
agent_sentinel/infrastructure/monitoring/__init__.py
agent_sentinel/infrastructure/monitoring/circuit_breaker.py
agent_sentinel/infrastructure/monitoring/data_sanitizer.py
agent_sentinel/infrastructure/monitoring/dev_weave_tracer.py
agent_sentinel/infrastructure/monitoring/metrics.py
agent_sentinel/infrastructure/monitoring/weave_service.py
agent_sentinel/intelligence/__init__.py
agent_sentinel/intelligence/agentic_orchestrator.py
agent_sentinel/intelligence/behavioral_analyzer.py
agent_sentinel/intelligence/enricher.py
agent_sentinel/intelligence/exa_service.py
agent_sentinel/intelligence/intelligence_types.py
agent_sentinel/intelligence/risk_scorer.py
agent_sentinel/logging/__init__.py
agent_sentinel/logging/structured_logger.py
agent_sentinel/models/__init__.py
agent_sentinel/models/detection_models.py
agent_sentinel/security/__init__.py
agent_sentinel/security/validators.py
agent_sentinel/services/__init__.py
agent_sentinel/services/detection_service.py
agent_sentinel/services/monitoring_service.py
agent_sentinel/wrappers/__init__.py
agent_sentinel/wrappers/agent_wrapper.py
agent_sentinel/wrappers/communication_wrapper.py
agent_sentinel/wrappers/decorators.py
agent_sentinel-0.4.0.dist-info/METADATA
agent_sentinel-0.4.0.dist-info/WHEEL
agent_sentinel-0.4.0.dist-info/entry_points.txt
agent_sentinel-0.4.0.dist-info/top_level.txt
agent_sentinel-0.4.0.dist-info/RECORD
